xsoar_dependency_graph/__init__.py
xsoar_dependency_graph/xsoar_dependency_graph.py
xsoar_dependency_graph/parsers/__init__.py
xsoar_dependency_graph/parsers/basic_parser.py
xsoar_dependency_graph/parsers/casetype_parser.py
xsoar_dependency_graph/parsers/integration_parser.py
xsoar_dependency_graph/parsers/layout_parser.py
xsoar_dependency_graph/parsers/pack_parser.py
xsoar_dependency_graph/parsers/playbook_parser.py
xsoar_dependency_graph/parsers/script_parser.py
xsoar_dependency_graph/utils/__init__.py
xsoar_dependency_graph/utils/ast_utils.py
xsoar_dependency_graph/utils/generic.py
xsoar_dependency_graph-0.2.0.dist-info/METADATA
xsoar_dependency_graph-0.2.0.dist-info/WHEEL
xsoar_dependency_graph-0.2.0.dist-info/licenses/LICENSE
xsoar_dependency_graph-0.2.0.dist-info/RECORD
