Metadata-Version: 2.4
Name: xsoar-dependency-graph
Version: 0.2.0
Summary: Creates and plots a dependency graph for XSOAR content packs.
Project-URL: Homepage, https://github.com/tlium/xsoar-dependency-graph
Project-URL: Issues, https://github.com/tlium/xsoar-dependency-graph/issues
Author-email: Torbjørn Lium <torben@lium.org>
License: MIT License
License-File: LICENSE
Keywords: graph,utilities,xsoar
Classifier: Programming Language :: Python
Classifier: Programming Language :: Python :: 3
Classifier: Programming Language :: Python :: 3.10
Classifier: Programming Language :: Python :: 3.11
Classifier: Programming Language :: Python :: 3.12
Requires-Dist: matplotlib>=3.0.0
Requires-Dist: networkx<3.0.0
Requires-Dist: numpy>=2.0.0
Requires-Dist: pyyaml>=6.0.0
Requires-Dist: scipy>=1.0.0
